mpsjobtracker/__init__.py
mpsjobtracker/schemas/__init__.py
mpsjobtracker/schemas/job_timestamp_schema.json
mpsjobtracker/schemas/job_tracker_init.json
mpsjobtracker/schemas/job_tracker_schema.json
mpsjobtracker/schemas/main_step_list.json
mpsjobtracker/schemas/main_step_list_schema.json
mpsjobtracker/schemas/master_step_list.json
mpsjobtracker/schemas/steps_schema.json
mpsjobtracker/tests/__init__.py
mpsjobtracker/tests/test.py
mpsjobtracker/trackers/__init__.py
mpsjobtracker/trackers/jobtracker.py
lts_mpsjobtracker-0.0.15.dist-info/LICENSE
lts_mpsjobtracker-0.0.15.dist-info/METADATA
lts_mpsjobtracker-0.0.15.dist-info/WHEEL
lts_mpsjobtracker-0.0.15.dist-info/top_level.txt
lts_mpsjobtracker-0.0.15.dist-info/RECORD
