Metadata-Version: 2.1
Name: lts-mpsjobtracker
Version: 0.0.15
Summary: A job tracker management module
Home-page: https://github.huit.harvard.edu/LTS/mps-job-tracker
Author: Katie Amaral
Author-email: kathryn_amaral@harvard.edu
License: UNKNOWN
Platform: UNKNOWN
Classifier: Programming Language :: Python :: 3
Classifier: License :: OSI Approved :: MIT License
Classifier: Operating System :: OS Independent
Requires-Python: >=3.6
Requires-Dist: uuid
Requires-Dist: jsonschema
